<?xml version="1.0" encoding="utf-8"?>
<data>
   <common>
      <threshold>-90</threshold>
      <frequency>2400</frequency>
      <redundancy>1</redundancy>
      <nodeNum>39</nodeNum>
   </common>
   <node>
      <no>1</no>
      <type>cd</type>
      <lon>132.676472</lon>
      <lat>34.509435</lat>
      <height>3.00</height>
      <connected>34,14,13,12,11,10,9</connected>
      <connectable>7</connectable>
   </node>
   <node>
      <no>2</no>
      <type>ed</type>
      <lon>132.667357</lon>
      <lat>34.511860</lat>
      <height>1.00</height>
      <connected>33,32,30,7,5</connected>
      <connectable>5</connectable>
   </node>
   <node>
      <no>3</no>
      <type>ed</type>
      <lon>132.672145</lon>
      <lat>34.512226</lat>
      <height>1.00</height>
      <connected>33</connected>
      <connectable>1</connectable>
   </node>
   <node>
      <no>4</no>
      <type>ed</type>
      <lon>132.672232</lon>
      <lat>34.510952</lat>
      <height>1.00</height>
      <connected>6</connected>
      <connectable>1</connectable>
   </node>
   <node>
      <no>5</no>
      <type>ed</type>
      <lon>132.668381</lon>
      <lat>34.510230</lat>
      <height>1.00</height>
      <connected>33,7,6,2</connected>
      <connectable>4</connectable>
   </node>
   <node>
      <no>6</no>
      <type>ed</type>
      <lon>132.671040</lon>
      <lat>34.509423</lat>
      <height>1.00</height>
      <connected>35,33,8,7,5,4</connected>
      <connectable>6</connectable>
   </node>
   <node>
      <no>7</no>
      <type>ed</type>
      <lon>132.667910</lon>
      <lat>34.509257</lat>
      <height>1.00</height>
      <connected>33,6,5,2</connected>
      <connectable>4</connectable>
   </node>
   <node>
      <no>8</no>
      <type>ed</type>
      <lon>132.672230</lon>
      <lat>34.507278</lat>
      <height>1.00</height>
      <connected>35,6</connected>
      <connectable>2</connectable>
   </node>
   <node>
      <no>9</no>
      <type>ed</type>
      <lon>132.675845</lon>
      <lat>34.510921</lat>
      <height>1.00</height>
      <connected>13,12,11,10,1</connected>
      <connectable>5</connectable>
   </node>
   <node>
      <no>10</no>
      <type>ed</type>
      <lon>132.676380</lon>
      <lat>34.511441</lat>
      <height>1.00</height>
      <connected>13,11,9,1</connected>
      <connectable>4</connectable>
   </node>
   <node>
      <no>11</no>
      <type>ed</type>
      <lon>132.677277</lon>
      <lat>34.511169</lat>
      <height>1.00</height>
      <connected>13,12,10,9,1</connected>
      <connectable>5</connectable>
   </node>
   <node>
      <no>12</no>
      <type>ed</type>
      <lon>132.678396</lon>
      <lat>34.511368</lat>
      <height>1.00</height>
      <connected>13,11,9,1</connected>
      <connectable>4</connectable>
   </node>
   <node>
      <no>13</no>
      <type>ed</type>
      <lon>132.677665</lon>
      <lat>34.510633</lat>
      <height>1.00</height>
      <connected>12,11,10,9,1</connected>
      <connectable>5</connectable>
   </node>
   <node>
      <no>14</no>
      <type>ed</type>
      <lon>132.676944</lon>
      <lat>34.508243</lat>
      <height>1.00</height>
      <connected>36,1</connected>
      <connectable>2</connectable>
   </node>
   <node>
      <no>15</no>
      <type>ed</type>
      <lon>132.682185</lon>
      <lat>34.510893</lat>
      <height>1.00</height>
      <connected>39</connected>
      <connectable>1</connectable>
   </node>
   <node>
      <no>16</no>
      <type>ed</type>
      <lon>132.683039</lon>
      <lat>34.504729</lat>
      <height>1.00</height>
      <connected>28,18,17</connected>
      <connectable>3</connectable>
   </node>
   <node>
      <no>17</no>
      <type>ed</type>
      <lon>132.684531</lon>
      <lat>34.503088</lat>
      <height>1.00</height>
      <connected>18</connected>
      <connectable>1</connectable>
   </node>
   <node>
      <no>18</no>
      <type>ed</type>
      <lon>132.685478</lon>
      <lat>34.504819</lat>
      <height>1.00</height>
      <connected>17,16</connected>
      <connectable>2</connectable>
   </node>
   <node>
      <no>19</no>
      <type>ed</type>
      <lon>132.662578</lon>
      <lat>34.512507</lat>
      <height>1.00</height>
      <connected>32,31</connected>
      <connectable>2</connectable>
   </node>
   <node>
      <no>20</no>
      <type>ed</type>
      <lon>132.684908</lon>
      <lat>34.506767</lat>
      <height>1.00</height>
      <connected>28</connected>
      <connectable>1</connectable>
   </node>
   <node>
      <no>21</no>
      <type>ed</type>
      <lon>132.673517</lon>
      <lat>34.503936</lat>
      <height>1.00</height>
      <connected>40,38</connected>
      <connectable>2</connectable>
   </node>
   <node>
      <no>22</no>
      <type>ed</type>
      <lon>132.679146</lon>
      <lat>34.501893</lat>
      <height>1.00</height>
      <connected>37</connected>
      <connectable>1</connectable>
   </node>
   <node>
      <no>23</no>
      <type>ed</type>
      <lon>132.677465</lon>
      <lat>34.500166</lat>
      <height>1.00</height>
      <connected>37,24</connected>
      <connectable>2</connectable>
   </node>
   <node>
      <no>24</no>
      <type>ed</type>
      <lon>132.675058</lon>
      <lat>34.501242</lat>
      <height>1.00</height>
      <connected>23</connected>
      <connectable>1</connectable>
   </node>
   <node>
      <no>25</no>
      <type>ed</type>
      <lon>132.684746</lon>
      <lat>34.510072</lat>
      <height>1.00</height>
      <connected>28</connected>
      <connectable>1</connectable>
   </node>
   <node>
      <no>26</no>
      <type>ed</type>
      <lon>132.662836</lon>
      <lat>34.508779</lat>
      <height>1.00</height>
      <connected>32,31,29</connected>
      <connectable>3</connectable>
   </node>
   <node>
      <no>27</no>
      <type>ed</type>
      <lon>132.660986</lon>
      <lat>34.506381</lat>
      <height>1.00</height>
      <connected>29</connected>
      <connectable>1</connectable>
   </node>
   <node>
      <no>28</no>
      <type>rt</type>
      <lon>132.683325</lon>
      <lat>34.507526</lat>
      <height>1.50</height>
      <connected>39,36,25,20,16</connected>
      <connectable>5</connectable>
   </node>
   <node>
      <no>29</no>
      <type>rt</type>
      <lon>132.661000</lon>
      <lat>34.506675</lat>
      <height>1.50</height>
      <connected>27,26</connected>
      <connectable>2</connectable>
   </node>
   <node>
      <no>30</no>
      <type>rt</type>
      <lon>132.664398</lon>
      <lat>34.510609</lat>
      <height>0.30</height>
      <connected>19,2</connected>
      <connectable>2</connectable>
   </node>
   <node>
      <no>31</no>
      <type>rt</type>
      <lon>132.670119</lon>
      <lat>34.510892</lat>
      <height>0.70</height>
      <connected>7,6,5,3,2</connected>
      <connectable>5</connectable>
   </node>
   <node>
      <no>32</no>
      <type>rt</type>
      <lon>132.674249</lon>
      <lat>34.509687</lat>
      <height>0.30</height>
      <connected>35,6,1</connected>
      <connectable>3</connectable>
   </node>
   <node>
      <no>33</no>
      <type>rt</type>
      <lon>132.672958</lon>
      <lat>34.507384</lat>
      <height>0.30</height>
      <connected>38,34,8,6</connected>
      <connectable>4</connectable>
   </node>
   <node>
      <no>34</no>
      <type>rt</type>
      <lon>132.679970</lon>
      <lat>34.506959</lat>
      <height>0.50</height>
      <connected>28,14</connected>
      <connectable>2</connectable>
   </node>
   <node>
      <no>35</no>
      <type>rt</type>
      <lon>132.677733</lon>
      <lat>34.502564</lat>
      <height>0.30</height>
      <connected>41,23,22</connected>
      <connectable>3</connectable>
   </node>
   <node>
      <no>36</no>
      <type>rt</type>
      <lon>132.673432</lon>
      <lat>34.504620</lat>
      <height>1.50</height>
      <connected>35,21</connected>
      <connectable>2</connectable>
   </node>
   <node>
      <no>37</no>
      <type>rt</type>
      <lon>132.681518</lon>
      <lat>34.509865</lat>
      <height>0.30</height>
      <connected>28,15</connected>
      <connectable>2</connectable>
   </node>
   <node>
      <no>38</no>
      <type>rt</type>
      <lon>132.676830</lon>
      <lat>34.503663</lat>
      <height>0.30</height>
      <connected>41,21</connected>
      <connectable>2</connectable>
   </node>
   <node>
      <no>39</no>
      <type>rt</type>
      <lon>132.677131</lon>
      <lat>34.503344</lat>
      <height>0.30</height>
      <connected>40,37</connected>
      <connectable>2</connectable>
   </node>
</data>
<!--this is a comment-->